CITATION.cff
LICENSE.txt
MANIFEST.in
README.md
pyproject.toml
requirements.dev.txt
requirements.ja.txt
requirements.notebooks.txt
requirements.txt
setup.cfg
setup.py
DTTS.egg-info/PKG-INFO
DTTS.egg-info/SOURCES.txt
DTTS.egg-info/dependency_links.txt
DTTS.egg-info/entry_points.txt
DTTS.egg-info/not-zip-safe
DTTS.egg-info/requires.txt
DTTS.egg-info/top_level.txt
TTS/.models.json
TTS/VERSION
TTS/__init__.py
TTS/api.py
TTS/cs_api.py
TTS/model.py
TTS/bin/__init__.py
TTS/bin/collect_env_info.py
TTS/bin/compute_attention_masks.py
TTS/bin/compute_embeddings.py
TTS/bin/compute_statistics.py
TTS/bin/eval_encoder.py
TTS/bin/extract_tts_spectrograms.py
TTS/bin/find_unique_chars.py
TTS/bin/find_unique_phonemes.py
TTS/bin/remove_silence_using_vad.py
TTS/bin/resample.py
TTS/bin/synthesize.py
TTS/bin/train_encoder.py
TTS/bin/train_tts.py
TTS/bin/train_vocoder.py
TTS/bin/tune_wavegrad.py
TTS/config/__init__.py
TTS/config/shared_configs.py
TTS/encoder/README.md
TTS/encoder/__init__.py
TTS/encoder/dataset.py
TTS/encoder/losses.py
TTS/encoder/configs/base_encoder_config.py
TTS/encoder/configs/emotion_encoder_config.py
TTS/encoder/configs/speaker_encoder_config.py
TTS/encoder/models/base_encoder.py
TTS/encoder/models/lstm.py
TTS/encoder/models/resnet.py
TTS/encoder/utils/__init__.py
TTS/encoder/utils/generic_utils.py
TTS/encoder/utils/io.py
TTS/encoder/utils/prepare_voxceleb.py
TTS/encoder/utils/training.py
TTS/encoder/utils/visual.py
TTS/server/README.md
TTS/server/__init__.py
TTS/server/conf.json
TTS/server/server.py
TTS/server/static/coqui-log-green-TTS.png
TTS/server/templates/details.html
TTS/server/templates/index.html
TTS/tts/__init__.py
TTS/tts/configs/__init__.py
TTS/tts/configs/align_tts_config.py
TTS/tts/configs/bark_config.py
TTS/tts/configs/delightful_tts_config.py
TTS/tts/configs/fast_pitch_config.py
TTS/tts/configs/fast_speech_config.py
TTS/tts/configs/fastspeech2_config.py
TTS/tts/configs/glow_tts_config.py
TTS/tts/configs/neuralhmm_tts_config.py
TTS/tts/configs/overflow_config.py
TTS/tts/configs/shared_configs.py
TTS/tts/configs/speedy_speech_config.py
TTS/tts/configs/tacotron2_config.py
TTS/tts/configs/tacotron_config.py
TTS/tts/configs/tortoise_config.py
