Metadata-Version: 2.1
Name: DTTS
Version: 0.16.5
Summary: Deep learning for Text to Speech by Coqui.
Home-page: https://github.com/coqui-ai/TTS
Author: Eren Gölge
Author-email: egolge@coqui.ai
License: MPL-2.0
Project-URL: Documentation, https://github.com/coqui-ai/TTS/wiki
Project-URL: Tracker, https://github.com/coqui-ai/TTS/issues
Project-URL: Repository, https://github.com/coqui-ai/TTS
Project-URL: Discussions, https://github.com/coqui-ai/TTS/discussions
Classifier: Programming Language :: Python
Classifier: Programming Language :: Python :: 3
Classifier: Programming Language :: Python :: 3.9
Classifier: Programming Language :: Python :: 3.10
Classifier: Programming Language :: Python :: 3.11
Classifier: Development Status :: 3 - Alpha
Classifier: Intended Audience :: Science/Research
Classifier: Intended Audience :: Developers
Classifier: Operating System :: POSIX :: Linux
Classifier: License :: OSI Approved :: Mozilla Public License 2.0 (MPL 2.0)
Classifier: Topic :: Software Development
Classifier: Topic :: Software Development :: Libraries :: Python Modules
Classifier: Topic :: Multimedia :: Sound/Audio :: Speech
Classifier: Topic :: Multimedia :: Sound/Audio
Classifier: Topic :: Multimedia
Classifier: Topic :: Scientific/Engineering :: Artificial Intelligence
Requires-Python: >=3.9.0, <3.12
Provides-Extra: all
Provides-Extra: dev
Provides-Extra: notebooks
Provides-Extra: ja
License-File: LICENSE.txt
